setup.py
transform_tools/__init__.py
transform_tools/validate.py
transform_tools.egg-info/PKG-INFO
transform_tools.egg-info/SOURCES.txt
transform_tools.egg-info/dependency_links.txt
transform_tools.egg-info/entry_points.txt
transform_tools.egg-info/requires.txt
transform_tools.egg-info/top_level.txt